iot/__init__.py
iot/core.py
iot/device.py
iot/devices/__init__.py
iot/devices/ali_genie.py
iot/devices/raspberry_pi.py
nonebot_plugin_iot-1.1.0.dist-info/LICENSE
nonebot_plugin_iot-1.1.0.dist-info/METADATA
nonebot_plugin_iot-1.1.0.dist-info/WHEEL
nonebot_plugin_iot-1.1.0.dist-info/top_level.txt
nonebot_plugin_iot-1.1.0.dist-info/RECORD
